README.rst
setup.py
emvis/__init__.py
emvis.egg-info/PKG-INFO
emvis.egg-info/SOURCES.txt
emvis.egg-info/dependency_links.txt
emvis.egg-info/entry_points.txt
emvis.egg-info/requires.txt
emvis.egg-info/top_level.txt
emvis/apps/__init__.py
emvis/apps/_utils.py
emvis/apps/picker.py
emvis/apps/viewer.py
emvis/models/__init__.py
emvis/models/_empicker.py
emvis/models/_emtable_model.py
emvis/models/_models_factory.py
emvis/tests/__init__.py
emvis/tests/test_columnview.py
emvis/tests/test_dataview.py
emvis/tests/test_dualimagelistview.py
emvis/tests/test_embrowser.py
emvis/tests/test_emtable.py
emvis/tests/test_galleryview.py
emvis/tests/test_image_export.py
emvis/tests/test_imagelistview.py
emvis/tests/test_imagemanager.py
emvis/tests/test_imagemasklistview.py
emvis/tests/test_imagemaskvolumelistview.py
emvis/tests/test_imagemodels.py
emvis/tests/test_imageview.py
emvis/tests/test_itemsview.py
emvis/tests/test_mask_creator.py
emvis/tests/test_matplotlib.py
emvis/tests/test_multi_columnview.py
emvis/tests/test_multislice_view.py
emvis/tests/test_picking_relion.py
emvis/tests/test_pickingviewdefault.py
emvis/tests/test_pickingviewfilament.py
emvis/tests/test_roimasklistview.py
emvis/tests/test_roimaskvolumelistview.py
emvis/tests/test_slices_view.py
emvis/tests/test_tvconfig.py
emvis/tests/test_volumelistview.py
emvis/tests/test_volumeview.py
emvis/utils/__init__.py
emvis/utils/_empath.py
emvis/utils/_emtype.py
emvis/utils/_image_manager.py
emvis/views/__init__.py
emvis/views/_box.py
emvis/views/_embrowser.py
emvis/views/_views_factory.py