Metadata-Version: 1.2
Name: emvis
Version: 0.0.4
Summary: Visualization tools for EM data analysis
Home-page: https://github.com/3dem/emvis
Author: J.M. De la Rosa Trevin,Pedro Hernandez Viga
Author-email: delarosatrevin@scilifelab.se, phviga2015@gmail.com
License: UNKNOWN
Project-URL: Bug Reports, https://github.com/3dem/emvis/issues
Project-URL: Source, https://github.com/3dem/emvis/
Platform: UNKNOWN
Classifier: Development Status :: 3 - Alpha
Classifier: License :: OSI Approved :: GNU General Public License v3 (GPLv3)
Classifier: Programming Language :: Python :: 3
